[
    {
        "title": "FESTIVAL DE ARROCES ! NEW YORK",
        "$id": "1333534951939",
        "description": "Este Viernes 25 de abril, 2025.",
        "$link": "https://www.eventbrite.com/e/festival-de-arroces-new-york-tickets-1333534951939",
        "$image_link": "https://img.evbuc.com/https%3A%2F%2Fcdn.evbuc.com%2Fimages%2F1013706333%2F2173328878303%2F1%2Foriginal.20250422-020859?crop=focalpoint&fit=crop&h=200&w=450&auto=format%2Ccompress&q=75&sharp=10&fp-x=5e-11&fp-y=5e-11&s=076374334a51cc87366846574a423aeb",
        "price": 0,
        "categories": []
    },
    {
        "title": "QUEENS 360 ! NEW YORK",
        "$id": "1301163257329",
        "description": "Este Viernes 25 de abril, 2025.",
        "$link": "https://www.eventbrite.com/e/queens-360-new-york-tickets-1301163257329",
        "$image_link": "https://img.evbuc.com/https%3A%2F%2Fcdn.evbuc.com%2Fimages%2F992332343%2F280240115497%2F1%2Foriginal.20250325-164203?crop=focalpoint&fit=crop&h=200&w=450&auto=format%2Ccompress&q=75&sharp=10&fp-x=0.005&fp-y=0.005&s=8d835c16ddec37a0ab01371e7aadcca8",
        "price": 0,
        "categories": []
    },
    {
        "title": "BIRTHDAY DASH ! NEW YORK",
        "$id": "1304944136039",
        "description": "Este Viernes 25 de abril, 2025.",
        "$link": "https://www.eventbrite.com/e/birthday-dash-new-york-tickets-1304944136039",
        "$image_link": "https://img.evbuc.com/https%3A%2F%2Fcdn.evbuc.com%2Fimages%2F1006381193%2F2173328878303%2F1%2Foriginal.20250411-000725?crop=focalpoint&fit=crop&h=200&w=450&auto=format%2Ccompress&q=75&sharp=10&fp-x=0.5&fp-y=0.5&s=8d2426684218d83d03e69a74fa937f9f",
        "price": 0,
        "categories": []
    },
    {
        "title": "YATCH CRUISE PARTY NY",
        "$id": "1304934246459",
        "description": "Este S\u00e1bado 26 de abril, 2025.",
        "$link": "https://www.eventbrite.com/e/yatch-cruise-party-ny-tickets-1304934246459",
        "$image_link": "https://img.evbuc.com/https%3A%2F%2Fcdn.evbuc.com%2Fimages%2F995556563%2F2173328878303%2F1%2Foriginal.20250329-031935?crop=focalpoint&fit=crop&h=200&w=450&auto=format%2Ccompress&q=75&sharp=10&fp-x=0.005&fp-y=0.005&s=141a171a5134f50b442573273fae0a2c",
        "price": 0,
        "categories": []
    },
    {
        "title": "NOCHE LATINA | NEW YORK",
        "$id": "1333547860549",
        "description": "Este S\u00e1bado 26 de abril, 2025.",
        "$link": "https://www.eventbrite.com/e/noche-latina-new-york-tickets-1333547860549",
        "$image_link": "https://img.evbuc.com/https%3A%2F%2Fcdn.evbuc.com%2Fimages%2F1013716393%2F2173328878303%2F1%2Foriginal.20250422-023430?crop=focalpoint&fit=crop&h=200&w=450&auto=format%2Ccompress&q=75&sharp=10&fp-x=5e-73&fp-y=5e-73&s=717d0d256034e85297b2ca0a6f6ae64d",
        "price": 0,
        "categories": []
    },
    {
        "title": "LOS ADOLESCENTES  NY",
        "$id": "1308205290239",
        "description": "Este S\u00e1bado 26 de abril, 2025.",
        "$link": "https://www.eventbrite.com/e/los-adolescentes-ny-tickets-1308205290239",
        "$image_link": "https://img.evbuc.com/https%3A%2F%2Fcdn.evbuc.com%2Fimages%2F1009921323%2F2173328878303%2F1%2Foriginal.20250416-000953?crop=focalpoint&fit=crop&h=200&w=450&auto=format%2Ccompress&q=75&sharp=10&fp-x=5e-05&fp-y=5e-05&s=7f3b6d87649536fe33580e987e3b60c4",
        "price": 0,
        "categories": []
    },
    {
        "title": "CONCURSO NACIONAL DEL CANTO ! NEW YORK",
        "$id": "1321908165909",
        "description": "Este Lunes 28 de abril, 2025.",
        "$link": "https://www.eventbrite.com/e/concurso-nacional-del-canto-new-york-tickets-1321908165909",
        "$image_link": "https://img.evbuc.com/https%3A%2F%2Fcdn.evbuc.com%2Fimages%2F1007195523%2F2173328878303%2F1%2Foriginal.20250411-233042?h=200&w=450&auto=format%2Ccompress&q=75&sharp=10&s=755fefba2b023de40b33eb89db78137a",
        "price": 0,
        "categories": []
    },
    {
        "title": "TRIBUTO A MANA NY",
        "$id": "1332646986009",
        "description": "Este S\u00e1bado 03 de mayo, 2025.",
        "$link": "https://www.eventbrite.com/e/tributo-a-mana-ny-tickets-1332646986009",
        "$image_link": "https://img.evbuc.com/https%3A%2F%2Fcdn.evbuc.com%2Fimages%2F1012974543%2F2173328878303%2F1%2Foriginal.20250421-015135?crop=focalpoint&fit=crop&h=200&w=450&auto=format%2Ccompress&q=75&sharp=10&fp-x=4.17518188774e-07&fp-y=6.91309828703e-08&s=c7964e42c6326a7622878e35c63bbc89",
        "price": 0,
        "categories": []
    },
    {
        "title": "GRAN CELEBRACION CINCO DE MAYO NY",
        "$id": "1320522962729",
        "description": "Este Domingo 04 de mayo, 2025.",
        "$link": "https://www.eventbrite.com/e/gran-celebracion-cinco-de-mayo-ny-tickets-1320522962729",
        "$image_link": "https://img.evbuc.com/https%3A%2F%2Fcdn.evbuc.com%2Fimages%2F1006276993%2F2173328878303%2F1%2Foriginal.20250410-212753?crop=focalpoint&fit=crop&h=200&w=450&auto=format%2Ccompress&q=75&sharp=10&fp-x=4.17518188774e-05&fp-y=6.91309828703e-06&s=b639519f34c4804de2efd217ed9a091c",
        "price": 0,
        "categories": []
    },
    {
        "title": "HANSEL CAMACHO ! EN QUEENS NY",
        "$id": "1280339061599",
        "description": "Este S\u00e1bado 10 de mayo, 2025.",
        "$link": "https://www.eventbrite.com/e/hansel-camacho-en-queens-ny-tickets-1280339061599",
        "$image_link": "https://img.evbuc.com/https%3A%2F%2Fcdn.evbuc.com%2Fimages%2F981422213%2F2173328878303%2F1%2Foriginal.20250312-005951?h=200&w=450&auto=format%2Ccompress&q=75&sharp=10&s=d0710e13a4ce16bed18c3874e7bca60e",
        "price": 0,
        "categories": []
    },
    {
        "title": "Cuando los Acordeones Lloran  Brentwood NY",
        "$id": "1333453237529",
        "description": "Este Viernes 30 de mayo, 2025.",
        "$link": "https://www.eventbrite.com/e/cuando-los-acordeones-lloran-brentwood-ny-tickets-1333453237529",
        "$image_link": "https://img.evbuc.com/https%3A%2F%2Fcdn.evbuc.com%2Fimages%2F1013629423%2F2173328878303%2F1%2Foriginal.20250421-234735?crop=focalpoint&fit=crop&h=200&w=450&auto=format%2Ccompress&q=75&sharp=10&fp-x=5e-13&fp-y=5e-13&s=a7e65ecce7372ce1a03cec0c05b6d04f",
        "price": 0,
        "categories": []
    }
]